probnum/.gitignore
probnum/__init__.py
probnum/_config.py
probnum/_version.py
probnum/conftest.py
probnum/typing.py
probnum/_pnmethod/__init__.py
probnum/_pnmethod/_probabilistic_numerical_method.py
probnum/_pnmethod/_stopping_criterion.py
probnum/diffeq/__init__.py
probnum/diffeq/_odesolution.py
probnum/diffeq/_odesolver.py
probnum/diffeq/_odesolver_state.py
probnum/diffeq/_perturbsolve_ivp.py
probnum/diffeq/_probsolve_ivp.py
probnum/diffeq/_utils.py
probnum/diffeq/callbacks/__init__.py
probnum/diffeq/callbacks/_callback.py
probnum/diffeq/callbacks/_discrete_callback.py
probnum/diffeq/odefilter/__init__.py
probnum/diffeq/odefilter/_odefilter.py
probnum/diffeq/odefilter/_odefilter_solution.py
probnum/diffeq/odefilter/approx_strategies/__init__.py
probnum/diffeq/odefilter/approx_strategies/_approx_strategy.py
probnum/diffeq/odefilter/approx_strategies/_ek.py
probnum/diffeq/odefilter/information_operators/__init__.py
probnum/diffeq/odefilter/information_operators/_approx_information_operator.py
probnum/diffeq/odefilter/information_operators/_information_operator.py
probnum/diffeq/odefilter/information_operators/_ode_residual.py
probnum/diffeq/odefilter/init_routines/__init__.py
probnum/diffeq/odefilter/init_routines/_autodiff.py
probnum/diffeq/odefilter/init_routines/_interface.py
probnum/diffeq/odefilter/init_routines/_non_probabilistic_fit.py
probnum/diffeq/odefilter/init_routines/_stack.py
probnum/diffeq/odefilter/utils/__init__.py
probnum/diffeq/odefilter/utils/_problem_utils.py
probnum/diffeq/perturbed/__init__.py
probnum/diffeq/perturbed/scipy_wrapper/__init__.py
probnum/diffeq/perturbed/scipy_wrapper/_wrapped_scipy_odesolution.py
probnum/diffeq/perturbed/scipy_wrapper/_wrapped_scipy_solver.py
probnum/diffeq/perturbed/step/__init__.py
probnum/diffeq/perturbed/step/_perturbation_functions.py
probnum/diffeq/perturbed/step/_perturbedstepsolution.py
probnum/diffeq/perturbed/step/_perturbedstepsolver.py
probnum/diffeq/stepsize/__init__.py
probnum-0.1.25.dist-info/LICENSE.txt
probnum-0.1.25.dist-info/METADATA
probnum-0.1.25.dist-info/WHEEL
probnum-0.1.25.dist-info/top_level.txt
probnum-0.1.25.dist-info/RECORD
