Metadata-Version: 2.1
Name: probnum
Version: 0.1.25
Summary: Probabilistic Numerics in Python.
License: The MIT License (MIT)
Project-URL: homepage, https://probnum.readthedocs.io/en/stable/
Project-URL: github, https://github.com/probabilistic-numerics/probnum
Project-URL: documentation, https://probnum.readthedocs.io/en/stable/
Project-URL: benchmarks, https://probabilistic-numerics.github.io/probnum-benchmarks/benchmarks/
Keywords: probabilistic-numerics,machine-learning,numerical-methods
Platform: any
Classifier: Development Status :: 4 - Beta
Classifier: License :: OSI Approved :: MIT License
Classifier: Operating System :: OS Independent
Classifier: Programming Language :: Python :: 3.8
Classifier: Programming Language :: Python :: 3.9
Classifier: Programming Language :: Python :: 3.10
Classifier: Programming Language :: Python :: 3.11
Requires-Python: <3.12,>=3.8
License-File: LICENSE.txt
Requires-Dist: numpy (>=1.20)
Requires-Dist: scipy (>=1.4)
Requires-Dist: numpy (>=1.21.3) ; python_version >= "3.10"
Requires-Dist: scipy (>=1.8.0) ; python_version >= "3.10"
Requires-Dist: numpy (>=1.24.0) ; python_version >= "3.11"
Requires-Dist: scipy (>=1.9.2) ; python_version >= "3.11"
Provides-Extra: full
Requires-Dist: tqdm (>=4.0) ; extra == 'full'
Requires-Dist: requests (>=2.0) ; extra == 'full'
Requires-Dist: pykeops (<3.0,>=2.1.1) ; extra == 'full'
Requires-Dist: jax[cpu] (<0.4.9) ; (platform_system != "Windows") and extra == 'full'
Provides-Extra: jax
Requires-Dist: jax[cpu] (<0.4.9) ; (platform_system != "Windows") and extra == 'jax'
Provides-Extra: keops
Requires-Dist: pykeops (<3.0,>=2.1.1) ; extra == 'keops'
Provides-Extra: zoo
Requires-Dist: tqdm (>=4.0) ; extra == 'zoo'
Requires-Dist: requests (>=2.0) ; extra == 'zoo'
Requires-Dist: jax[cpu] (<0.4.9) ; (platform_system != "Windows") and extra == 'zoo'
